baygaud/__init__.py
baygaud/_baygaud_params.py
baygaud/_dynesty_sampler.py
baygaud/_fits_io.py
baygaud/_plot.py
baygaud/baygaud.py
baygaud/combine_segs.py
baygaud-0.1.9.dist-info/DESCRIPTION.rst
baygaud-0.1.9.dist-info/METADATA
baygaud-0.1.9.dist-info/RECORD
baygaud-0.1.9.dist-info/WHEEL
baygaud-0.1.9.dist-info/metadata.json
baygaud-0.1.9.dist-info/top_level.txt
